prophecy_deploy_cli/__init__.py
prophecy_deploy_cli-1.0.1.dist-info/METADATA
prophecy_deploy_cli-1.0.1.dist-info/WHEEL
prophecy_deploy_cli-1.0.1.dist-info/top_level.txt
prophecy_deploy_cli-1.0.1.dist-info/RECORD
