Metadata-Version: 2.4
Name: prophecy-deploy-cli
Version: 1.0.1
Summary: Prophecy Deploy CLI Complete Package (JPMC)
Author-email: Prophecy <support@prophecy.io>
License: Proprietary
Project-URL: Homepage, https://prophecy.io
Project-URL: Repository, https://github.com/prophecy-io/prophecy-deploy-cli-binary
Keywords: prophecy,deploy,cli,binary
Classifier: Programming Language :: Python :: 3
Classifier: License :: Other/Proprietary License
Classifier: Operating System :: POSIX :: Linux
Requires-Python: >=3.8
Requires-Dist: prophecy-deploy-cli-executable>=1.0.1
Requires-Dist: prophecy-deploy-cli-config>=1.0.1
Requires-Dist: prophecy-deploy-cli-deps>=1.0.1
